{"ModuleName":"Module 17","CatInfos":[{"CatName":"A","QuestionRequired":[16,0,0],"TimeLimit":10},{"CatName":"B1","QuestionRequired":[8,0,0],"TimeLimit":45},{"CatName":"B2","QuestionRequired":[8,0,0],"TimeLimit":45}],"Questions":[{"Index":1,"QuestionString":"High speed propellers are designed to. (Level 1)","Answers":["rotate at high RPM.","operate at high forward speeds.","operate at supersonic tip speeds."],"Level":1,"CorrectAnswer":2},{"Index":2,"QuestionString":"When in the windmill position ATM. (Level 1)","Answers":["opposes CTM.","is not related to CTM.","assists CTM."],"Level":1,"CorrectAnswer":3},{"Index":3,"QuestionString":"The optimum angle for a fixed pitch propeller is. (Level 1)","Answers":["15 degrees.","2 - 4 degrees.","6 - 10 degrees."],"Level":1,"CorrectAnswer":2},{"Index":4,"QuestionString":"A left handed propeller is one that. (Level 1)","Answers":["rotates clockwise when viewed from the rear.","rotates clockwise when viewed from the front.","is fitted to an engine on the left side of the aircraft."],"Level":1,"CorrectAnswer":2},{"Index":5,"QuestionString":"Forces acting on a propeller are. (Level 1)","Answers":["centrifugal, twisting, and bending.","torque, thrust and centrifugal.","torsion, tension and thrust."],"Level":1,"CorrectAnswer":1},{"Index":6,"QuestionString":"The blade angle at the root is. (Level 1)","Answers":["less than the tip.","same from tip to root.","greater than the tip."],"Level":1,"CorrectAnswer":3},{"Index":7,"QuestionString":"What force on a propeller blade turns the blades to a fine pitch?. (Level 2)","Answers":["ATM.","Torque.","CTM."],"Level":2,"CorrectAnswer":3},{"Index":8,"QuestionString":"The purpose of propeller twist is. (Level 2)","Answers":["coarsen the blade angle at the root.","to maintain Blade Angle along the blade.","to maintain Angle of Attack at the same value along the blade."],"Level":2,"CorrectAnswer":3},{"Index":9,"QuestionString":"The forces acting on a propeller blade are. (Level 2)","Answers":["bending, twisting and centrifugal.","thrust, aerodynamic and tension.","thrust and torque."],"Level":2,"CorrectAnswer":1},{"Index":10,"QuestionString":"Blade angle at the root is. (Level 2)","Answers":["low.","high.","master blade angle."],"Level":2,"CorrectAnswer":2},{"Index":11,"QuestionString":"Blade angle is taken from the chord and. (Level 2)","Answers":["propeller shaft.","relative airflow.","plane of rotation."],"Level":2,"CorrectAnswer":3},{"Index":12,"QuestionString":"What forces act on a propeller blade?. (Level 2)","Answers":["Thrust and torque.","Bending, thrust, torque.","Bending, CTM and ATM."],"Level":2,"CorrectAnswer":3},{"Index":13,"QuestionString":"A fibreglass composite blade. (Level 1)","Answers":["will never be struck by lighting.","does not require lightning strike protection.","requires lightning strike protection."],"Level":1,"CorrectAnswer":3},{"Index":14,"QuestionString":"The timber most often used today for propeller construction is. (Level 1)","Answers":["birch.","spruce.","balsa."],"Level":1,"CorrectAnswer":1},{"Index":15,"QuestionString":"Electronic torque measuring systems utilise. (Level 1)","Answers":["strain gauges in the reduction gear.","stress gauges in the reduction gear.","pressure transducers in the reduction gear."],"Level":1,"CorrectAnswer":1},{"Index":16,"QuestionString":"A conventional turboprop torque meter uses. (Level 1)","Answers":["hydraulic oil as the pressure medium.","coiled spring levers as the pressure medium.","engine oil as the pressure medium."],"Level":1,"CorrectAnswer":3},{"Index":17,"QuestionString":"Metal at the tip and along the leading edge of a wooden propeller is. (Level 1)","Answers":["for balancing.","for protection.","for Anti-icing."],"Level":1,"CorrectAnswer":2},{"Index":18,"QuestionString":"Blade cuffs are fitted to the root of the blades. (Level 1)","Answers":["to increase the strength of the blade.","to increase thrust.","to increase flow of cooling air into the engine nacelle."],"Level":1,"CorrectAnswer":3},{"Index":19,"QuestionString":"Low torque sensing is used to. (Level 2)","Answers":["increase power.","increase pitch.","initiate auto-feather."],"Level":2,"CorrectAnswer":3},{"Index":20,"QuestionString":"Torque sensing is used to. (Level 2)","Answers":["reduce drag.","reduce drag following engine shutdown.","synchronise blade angle."],"Level":2,"CorrectAnswer":2},{"Index":21,"QuestionString":"The minimum percentage seating on a propeller rear cone should be. (Level 2)","Answers":["90%.","70%.","95%."],"Level":2,"CorrectAnswer":2},{"Index":22,"QuestionString":"The propeller is 'feathered' when the blades are at. (Level 2)","Answers":["0° to plane of rotation.","20° to plane of rotation.","90° to plane of rotation."],"Level":2,"CorrectAnswer":3},{"Index":23,"QuestionString":"The thrust of a propeller is normally taken by the. (Level 2)","Answers":["torque meter.","propeller rear cone.","front bearing in the reduction gear."],"Level":2,"CorrectAnswer":3},{"Index":24,"QuestionString":"On which type of turbo-propeller would you expect to find a parking brake?. (Level 2)","Answers":["Compounded twin spool.","Direct coupled twin spool.","Free turbine."],"Level":2,"CorrectAnswer":3},{"Index":25,"QuestionString":"When the compressive force on a speeder spring is reduced, the propeller blades will. (Level 1)","Answers":["remain fixed.","fine off.","coarsen."],"Level":1,"CorrectAnswer":3},{"Index":26,"QuestionString":"A hydraulic pitch lock is utilised in a hydromatic propeller to. (Level 1)","Answers":["lock out the course pitch oil line in the event of underspeeding.","lock out the fine pitch oil line in the event of overspeeding.","prevent the propeller overspeeding in the event of oil supply failure."],"Level":1,"CorrectAnswer":2},{"Index":27,"QuestionString":"When in the beta range, the propeller pitch is controlled. (Level 1)","Answers":["directly from the power lever.","indirectly from the power lever.","directly from the pitch change mechanism to the PCU."],"Level":1,"CorrectAnswer":1},{"Index":28,"QuestionString":"The advantage of the beta range is it allows. (Level 1)","Answers":["high power settings with higher than normal pitch settings when in flight.","low fine pitch settings with high power.","low power settings with higher than normal pitch setting for ground manoeuvres."],"Level":1,"CorrectAnswer":3},{"Index":29,"QuestionString":"If the speeder spring pressure of a CSU is increased the blade will. (Level 1)","Answers":["coarsen off.","fine off.","will not move."],"Level":1,"CorrectAnswer":2},{"Index":30,"QuestionString":"On an underspeed condition the blades are turned to. (Level 1)","Answers":["fine.","feather.","coarse."],"Level":1,"CorrectAnswer":1},{"Index":31,"QuestionString":"Synchrophasing reduces vibration by the use of. (Level 1)","Answers":["pulse probes and a single synchrophase unit.","tachometers and correction motors.","coordinating the rpm of each engine."],"Level":1,"CorrectAnswer":1},{"Index":32,"QuestionString":"Synchronising can only be achieved if the slave propeller is. (Level 1)","Answers":["the same speed as the master.","within 20 rpm of the master.","within 100 rpm of the master."],"Level":1,"CorrectAnswer":3},{"Index":33,"QuestionString":"Synchronising is carried out to. (Level 1)","Answers":["match propeller tip speed.","match engine rpm.","match blade phase angle difference."],"Level":1,"CorrectAnswer":1},{"Index":34,"QuestionString":"The synchronisation governor monitors. (Level 1)","Answers":["RPM.","propeller tip speeds.","thrust tip speeds."],"Level":1,"CorrectAnswer":1},{"Index":35,"QuestionString":"Synchronisation is used to. (Level 1)","Answers":["reduce vibration and noise.","reduce the pitch of the fastest running blade.","preset the phase angle of propellers."],"Level":1,"CorrectAnswer":1},{"Index":36,"QuestionString":"Synchronisation is used. (Level 1)","Answers":["on the ground.","in flight except landing and take off.","in flight."],"Level":1,"CorrectAnswer":2},{"Index":37,"QuestionString":"The propeller synchronising system is put into operation by. (Level 2)","Answers":["adjusting the engine rpm at required cruise speed then switching on the synchroniser.","adjusting the engine rpm then propeller rpm to required speed then switching on.","switching on the synchronizer then adjust the engine rpm so that all engines adjust together."],"Level":2,"CorrectAnswer":1},{"Index":38,"QuestionString":"Propellers are synchronised by the. (Level 2)","Answers":["power lever.","PCU governor.","prop lever."],"Level":2,"CorrectAnswer":2},{"Index":39,"QuestionString":"Unlike the automatic synchronizing system, the synchrophasing system of a twopropeller aircraft. (Level 2)","Answers":["sets the blade phase angle of two constant speed propellers.","causes the same rotation speed of the two propellers.","matches the blade angle of variable pitch propellers."],"Level":2,"CorrectAnswer":1},{"Index":40,"QuestionString":"In a propeller synchrophasing system, an electric actuator. (Level 2)","Answers":["rotates (controls) the slave engine governor.","equalizes the governor signals.","turns the flexible shaft leading to the trimmer assembly."],"Level":2,"CorrectAnswer":1},{"Index":41,"QuestionString":"If one signal is lost into the comparator unit when Synchrophasing is operating. (Level 2)","Answers":["Synchrophasing is lost and the engines continue to function normally.","the slower engine immediately goes to feather.","both engines remain running until there is a difference, of commonly, (4 to 5 percent), at which the slower of the engines is then feathered."],"Level":2,"CorrectAnswer":1},{"Index":42,"QuestionString":"Synchronisation controls RPM within what range?. (Level 2)","Answers":["100 RPM.","150 RPM.","50 RPM."],"Level":2,"CorrectAnswer":1},{"Index":43,"QuestionString":"Electrically de-iced propeller slip rings have regular resistance checks for. (Level 1)","Answers":["oxidisation due to altitude.","open circuit heating elements.","wear between brushes and slip ring."],"Level":1,"CorrectAnswer":2},{"Index":44,"QuestionString":"Propeller anti-icing may be achieved by. (Level 1)","Answers":["using iso-propyl alcohol de-icing fluid sprayed on the blade.","using commercial de-icing fluid sprayed on the pro.","a using hot air from the compressor."],"Level":1,"CorrectAnswer":1},{"Index":45,"QuestionString":"De-icing of the propeller can be monitored by. (Level 1)","Answers":["viewing the deicing fluid level sight glass.","viewing the blade and observing ice falling off the blade.","an ammeter in the flight deck."],"Level":1,"CorrectAnswer":3},{"Index":46,"QuestionString":"Insulation testing of electrical de-icing systems should be periodically carried out because of. (Level 1)","Answers":["an open circuit in one of the blades.","oxidation due to atmospheric conditions.","wear on the slip rings."],"Level":1,"CorrectAnswer":1},{"Index":47,"QuestionString":"Insulation checks on propeller electrical heating elements should be carried out frequently due to. (Level 1)","Answers":["short/open circuits in the heating system wires along the propeller blade.","oxidation of slip ring and brush gear assembly.","deposits formed due to the wear of slip ring and brush gear assembly."],"Level":1,"CorrectAnswer":1},{"Index":48,"QuestionString":"Where is the de-icing boot?. (Level 1)","Answers":["Root.","Trailing edge.","Tip."],"Level":1,"CorrectAnswer":1},{"Index":49,"QuestionString":"How is anti icing fluid fed to the individual blades?. (Level 2)","Answers":["Pump to a slinger ring.","Pump to each blade rubber feed boot.","Under gravity to the slinger ring then on to the blade."],"Level":2,"CorrectAnswer":1},{"Index":50,"QuestionString":"Ice is removed from blades by. (Level 2)","Answers":["a continuously heated electrical boot.","rubber boots inflated in sequence using compressor hot air.","inboard and outboard boot sections heated in sequence by action of the timer."],"Level":2,"CorrectAnswer":3},{"Index":51,"QuestionString":"Propeller blades are de-iced by. (Level 2)","Answers":["electrical heating elements bound in rubber overshoes on the blade leading edges.","generating eddy currents in the blade.","electrical heating elements wound around rubber shoes."],"Level":2,"CorrectAnswer":1},{"Index":52,"QuestionString":"Electrical power supplies on large aircraft, for electrical deicing are. (Level 2)","Answers":["AC.","DC.","Both AC or DC."],"Level":2,"CorrectAnswer":2},{"Index":53,"QuestionString":"Propeller slip rings. (Level 2)","Answers":["convey oil for PCU to pitch change mechanism.","minimise slip.","conduct electrical power for de-icing."],"Level":2,"CorrectAnswer":3},{"Index":54,"QuestionString":"On an electrical deicing system fast cycle is used. (Level 2)","Answers":["at low air temperature.","at high air temperature.","on the ground."],"Level":2,"CorrectAnswer":2},{"Index":55,"QuestionString":"Thrust and camber faces of a propeller should be blended out to. (Level 3)","Answers":["5 times the depth of damage.","10 times to the depth of damage.","30 times to the depth of damage."],"Level":3,"CorrectAnswer":3},{"Index":56,"QuestionString":"An aerodynamic correction factor that is preceded by the letter Q indicates. (Level 3)","Answers":["thrust balance.","dynamic balance.","torque balance."],"Level":3,"CorrectAnswer":3},{"Index":57,"QuestionString":"Leading edges should be blended out to. (Level 3)","Answers":["5 times the depth of damage.","10 times the depth of damage.","30 times the depth of damage."],"Level":3,"CorrectAnswer":2},{"Index":58,"QuestionString":"If the tip of an electrical overshoe is torn. (Level 3)","Answers":["it may be cut back.","it may be classified as acceptable damage.","it must not be cut back."],"Level":3,"CorrectAnswer":3},{"Index":59,"QuestionString":"The shank of the propeller is permitted to have. (Level 3)","Answers":["no repairs.","minor repairs.","no decals fitted."],"Level":3,"CorrectAnswer":1},{"Index":60,"QuestionString":"When blending out a gouge on the face or camber side of a blade, the additional metal to be removed for stress relief is. (Level 3)","Answers":["0.02 inch.","0.002 inch.","0.2 inch."],"Level":3,"CorrectAnswer":2},{"Index":61,"QuestionString":"Wooden propellers are permitted. (Level 3)","Answers":["repairs that do not affect weight and balance.","no repairs.","repairs using sawdust and aeroglue."],"Level":3,"CorrectAnswer":3},{"Index":62,"QuestionString":"The preservative used to protect metal blades is. (Level 3)","Answers":["lanolin.","brown storage wax.","petroleum jelly."],"Level":3,"CorrectAnswer":1},{"Index":63,"QuestionString":"Composite propellers may have minor repairs carried out by. (Level 3)","Answers":["any approved 3rd party maintenance organization.","the operator.","any approved composite repair facility."],"Level":3,"CorrectAnswer":3},{"Index":64,"QuestionString":"Details of propeller overhaul may be found in. (Level 3)","Answers":["Airworthiness Notice 75.","the AMM.","Airworthiness Notice 55."],"Level":3,"CorrectAnswer":1},{"Index":65,"QuestionString":"The ground clearance of a single engine tail wheel aircraft propeller is measured with the aircraft. (Level 3)","Answers":["tail wheel on the ground.","tail wheel in the take off position.","in the rigging position."],"Level":3,"CorrectAnswer":2},{"Index":66,"QuestionString":"The structural clearance of a multi engine aircraft propeller. (Level 3)","Answers":["is taken between the engines with the props aligned.","is taken between the prop and the fuselage.","is taken from the ground."],"Level":3,"CorrectAnswer":2},{"Index":67,"QuestionString":"What position should the blades be when installing the pitch change mechanism onto a hydromatic propeller?. (Level 3)","Answers":["Feather.","Zero pitch.","Full reverse."],"Level":3,"CorrectAnswer":1},{"Index":68,"QuestionString":"The ground (sea) clearance of a sea plane propeller is. (Level 3)","Answers":["1 inch.","9 inches.","18 inches."],"Level":3,"CorrectAnswer":3},{"Index":69,"QuestionString":"Cropping is permitted to a maximum of. (Level 3)","Answers":["1 inch on all blades.","½ inch on all blades.","½ inch on one blade only."],"Level":3,"CorrectAnswer":1},{"Index":70,"QuestionString":"Dynamic balance is confirmed by use of. (Level 3)","Answers":["knife edges and mandrel.","a tracking check.","a vibration analyser."],"Level":3,"CorrectAnswer":3},{"Index":71,"QuestionString":"A metal propeller may be statically balanced by. (Level 3)","Answers":["adding varnish to the lighter blade.","removing metal from the opposite blade.","adding or removing lead wool to the hollow blade roots."],"Level":3,"CorrectAnswer":3},{"Index":72,"QuestionString":"Mechanical vibration relating to propellers in a piston powered aircraft. (Level 3)","Answers":["is due to the crankshaft at intermittent power settings.","is due to the lead lag of the propeller compared to the engine.","is due to the power stroke of the engine and may have a more detrimental effect than aerodynamic vibration."],"Level":3,"CorrectAnswer":3},{"Index":73,"QuestionString":"Aerodynamic Correction Factor (A C F). (Level 3)","Answers":["corrects for static balance.","is indicated in the form of degrees and minutes of pitch.","corrects for dynamic balance."],"Level":3,"CorrectAnswer":2},{"Index":74,"QuestionString":"A propeller with an adjustable blade can be adjusted. (Level 3)","Answers":["on the ground with the engine stationary.","in flight.","on the ground with the engine running."],"Level":3,"CorrectAnswer":1},{"Index":75,"QuestionString":"When on the ground with the engine idling the prop control should be. (Level 3)","Answers":["fully aft with the mixture at idle.","fully aft with the mixture at rich.","fully forward with the mixture at idle."],"Level":3,"CorrectAnswer":2},{"Index":76,"QuestionString":"Operation with the engine at maximum boost should be limited to. (Level 3)","Answers":["prop at fine to prevent overstressing the engine.","prop at course to prevent overstressing the engine.","prop at windmill to prevent overstressing the engine."],"Level":3,"CorrectAnswer":2},{"Index":77,"QuestionString":"Damage to a leading edge can be blended in comparison to a blade face. (Level 3)","Answers":["by maintaining a smooth depression.","by not exceeding 25% of the chord.","at a steeper angle."],"Level":3,"CorrectAnswer":3},{"Index":78,"QuestionString":"The longitudinal clearance between the nose wheel and the propeller on a tricycle geared propeller is. (Level 3)","Answers":["9 inches.","18 inches.","1/2 inch."],"Level":3,"CorrectAnswer":3},{"Index":79,"QuestionString":"A tracking check compares. (Level 3)","Answers":["2 Adjacent blades.","2 Opposite blades.","any 2 blades."],"Level":3,"CorrectAnswer":3},{"Index":80,"QuestionString":"A line of indentations at one blade section can be. (Level 3)","Answers":["blended within limits.","left for up to 12 months.","declared unserviceable."],"Level":3,"CorrectAnswer":3},{"Index":81,"QuestionString":"Propeller vibration due to a problem with propeller installations would have a. (Level 3)","Answers":["the same frequency as turbine vibration.","lower frequency than turbine vibration.","higher frequency than turbine vibration."],"Level":3,"CorrectAnswer":2},{"Index":82,"QuestionString":"Preloading propeller blades before installation prevents. (Level 3)","Answers":["blade distortion.","blade flutter.","aerodynamic imbalance on the blades."],"Level":3,"CorrectAnswer":2},{"Index":83,"QuestionString":"When unfeathering a propeller, the blade should be put into what position to stop propeller overspeed?. (Level 3)","Answers":["Negative pitch.","Fine pitch.","Coarse pitch."],"Level":3,"CorrectAnswer":3},{"Index":84,"QuestionString":"Blade angle is measured using a. (Level 3)","Answers":["clinometer.","propeller protractor.","bevel protractor."],"Level":3,"CorrectAnswer":2},{"Index":85,"QuestionString":"In the Beta range, angle of attack increases. The fuel flow increases, and what else increases?. (Level 3)","Answers":["Fuel temperature.","EPR and fuel temperature.","RPM and EGT."],"Level":3,"CorrectAnswer":3},{"Index":86,"QuestionString":"With a propeller defect, the frequency of vibration will be. (Level 3)","Answers":["higher than a auxiliary gearbox defect.","lower than a turbine defect.","higher than a turbine defect."],"Level":3,"CorrectAnswer":2},{"Index":87,"QuestionString":"Blending of propeller blade defects refers to the. (Level 3)","Answers":["repainting of blade tips after cropping.","matching of paint finishes for appearances.","conversion of rough or sharp edges into smooth depression."],"Level":3,"CorrectAnswer":3},{"Index":88,"QuestionString":"Removal of material from the propeller blade tips, resulting in a reduction in propeller diameter is called. (Level 2)","Answers":["tipping.","cropping.","topping."],"Level":2,"CorrectAnswer":2},{"Index":89,"QuestionString":"Prior to using the universal propeller protractor. (Level 2)","Answers":["ensure the propeller blade is at the horizontal.","determine the reference blade station.","check date stamp for serviceability."],"Level":2,"CorrectAnswer":2},{"Index":90,"QuestionString":"To fit a new front cone to a prop shaft firstly. (Level 2)","Answers":["etch the propeller serial number to the rear face.","cut in half with a hacksaw and etch a unique serial number to both halves.","coat in Engineers blue to ensure seating in the propeller front boss."],"Level":2,"CorrectAnswer":2},{"Index":91,"QuestionString":"Blade tracking is adjusted by. (Level 2)","Answers":["adding lead wool to the blade shank.","re-seating the propeller on the front and rear cones.","by fitting shims to the propeller shaft hub."],"Level":2,"CorrectAnswer":3},{"Index":92,"QuestionString":"Which of the following functions requires the use of a propeller blade station?. (Level 2)","Answers":["Indexing blades.","Propeller balancing.","Measuring blade angle."],"Level":2,"CorrectAnswer":3},{"Index":93,"QuestionString":"To conduct a power check of an internal combustion engine requires. (Level 2)","Answers":["coarse pitch setting and advance the throttle to the target RPM.","fine pitch setting and advance the engine to the target RPM setting.","fine pitch setting and advance the engine to the max RPM setting."],"Level":2,"CorrectAnswer":2},{"Index":94,"QuestionString":"The power output of a turboprop engine is checked by. (Level 2)","Answers":["reference RPM.","reference Thrust.","reference Torque."],"Level":2,"CorrectAnswer":3},{"Index":95,"QuestionString":"Immediately after blending out damage to to a blade the repair must be. (Level 2)","Answers":["re-protected against corrosion.","crack checked.","balanced."],"Level":2,"CorrectAnswer":2},{"Index":96,"QuestionString":"How is the efficiency of a turbo prop engine assessed?. (Level 2)","Answers":["By correcting propeller RPM for ambient Air temperature and barometric pressure.","By comparing compressor and propeller RPM against a reference figure.","By comparing torque meter pressure against a reference figure."],"Level":2,"CorrectAnswer":1},{"Index":97,"QuestionString":"The limits for a tracking check are. (Level 2)","Answers":["1/4 inch maximum difference between adjacent blades.","1/8 inch maximum difference between opposite blades.","1/8 inch maximum difference between all blades."],"Level":2,"CorrectAnswer":3},{"Index":98,"QuestionString":"After a lightning strike. (Level 2)","Answers":["the prop must be tracked.","the propeller shaft should be checked for concentricity.","the heater elements should be checked for continuity and insulation."],"Level":2,"CorrectAnswer":3},{"Index":99,"QuestionString":"After overspeeding to 110%. (Level 2)","Answers":["no action is required.","return propeller for overhaul.","remove propeller for inspection."],"Level":2,"CorrectAnswer":1},{"Index":100,"QuestionString":"Indentations to the blade face are measured. (Level 2)","Answers":["individually.","individually and collectively.","collectively."],"Level":2,"CorrectAnswer":2},{"Index":101,"QuestionString":"When a propeller has had a report of overspeeding. (Level 2)","Answers":["procedure is dependant on the extent of overspeeding.","the propeller must be removed and sent to the manufacturer.","the propeller must be removed and tracked."],"Level":2,"CorrectAnswer":1},{"Index":102,"QuestionString":"The most significant effect of stone chips on a propeller is. (Level 2)","Answers":["thrust output of the propeller.","structural integrity of the propeller.","aerodynamic capability of the propeller."],"Level":2,"CorrectAnswer":2},{"Index":103,"QuestionString":"Rubber components should be stored in. (Level 2)","Answers":["the dark.","natural light.","flouresent light."],"Level":2,"CorrectAnswer":1},{"Index":104,"QuestionString":"The maximum storage periods for installed propellers are detailed in the. (Level 2)","Answers":["propeller overhaul and repair manual.","Airworthiness Notices.","aircraft Maintenance Manual."],"Level":2,"CorrectAnswer":3},{"Index":105,"QuestionString":"When storing wooden propellers. (Level 2)","Answers":["store in a dry well ventilated and illuminated location.","store in a horizontal position.","wrap in greaseproof paper."],"Level":2,"CorrectAnswer":2},{"Index":106,"QuestionString":"A wooden propeller should be stored. (Level 1)","Answers":["a dry and well ventilated area.","in a room with high humidity to stop it drying and cracking.","a warm but light storeroom."],"Level":1,"CorrectAnswer":1},{"Index":107,"QuestionString":"A wooden propeller in storage. (Level 1)","Answers":["should not be wrapped at-all.","should be wrapped tightly.","should be wrapped loosely."],"Level":1,"CorrectAnswer":1},{"Index":108,"QuestionString":"A VP propeller mechanism, for storage for long periods should. (Level 1)","Answers":["should be completely emptied and dried.","be filled with special inhibiting oil to prevent condensation and corrosion.","be filled with the normal operating oil to prevent condensation and corrosion."],"Level":1,"CorrectAnswer":1}]}